kickoff/__init__.py
kickoff/__main__.py
kickoff/builder.py
kickoff/cmdpath.py
kickoff/exceptions.py
kickoff/helpers.py
kickoff/inspectutils.py
kickoff/loader.py
kickoff/logger.py
kickoff/shared.py
kickoff-0.1.0.dist-info/METADATA
kickoff-0.1.0.dist-info/WHEEL
kickoff-0.1.0.dist-info/entry_points.txt
kickoff-0.1.0.dist-info/top_level.txt
kickoff-0.1.0.dist-info/RECORD
