Metadata-Version: 2.1
Name: kickoff
Version: 0.1.0
Summary: Turns your Python script or module into an application with decent CLI.
Home-page: https://github.com/gergelyk/python-kickoff
Author: Grzegorz Krason
Author-email: grzegorz.krason@gmail.com
License: MIT
Keywords: cli,cui,argparse,optparse,docopt,click,fire,invoke,runfile
Platform: UNKNOWN
Classifier: Environment :: Console
Classifier: Environment :: MacOS X
Classifier: Environment :: Other Environment
Classifier: Environment :: Win32 (MS Windows)
Classifier: Intended Audience :: Developers
Classifier: License :: Freeware
Classifier: License :: OSI Approved :: MIT License
Classifier: Operating System :: iOS
Classifier: Operating System :: MacOS
Classifier: Operating System :: Microsoft :: Windows
Classifier: Operating System :: POSIX
Classifier: Operating System :: Unix
Classifier: Programming Language :: Python :: 3
Classifier: Programming Language :: Python :: 3.6
Classifier: Programming Language :: Python :: 3.7
Classifier: Programming Language :: Python :: 3.8
Classifier: Programming Language :: Python :: 3 :: Only
Classifier: Topic :: Software Development
Classifier: Topic :: Software Development :: Libraries :: Python Modules
Requires-Python: ~=3.6
Requires-Dist: click
Requires-Dist: python-box
